ThunderFlowPro/ConFunctions.py
ThunderFlowPro/ConstantsConsumption.py
ThunderFlowPro/VehicleConstants.py
ThunderFlowPro/__init__.py
ThunderFlowPro-0.1.2.dist-info/LICENSE.txt
ThunderFlowPro-0.1.2.dist-info/METADATA
ThunderFlowPro-0.1.2.dist-info/WHEEL
ThunderFlowPro-0.1.2.dist-info/top_level.txt
ThunderFlowPro-0.1.2.dist-info/RECORD
