Metadata-Version: 2.1
Name: ThunderFlowPro
Version: 0.1.2
Summary: Consumption estimation EV battery
Home-page: https://github.com/cordeiroandres/ThunderFlowPro
Author: Andres Cordeiro
Author-email: cordeiroandres@gmail.com
License: MIT
Classifier: License :: OSI Approved :: MIT License
Classifier: Programming Language :: Python :: 3
Classifier: Operating System :: OS Independent
Requires-Python: >=3.8.13
License-File: LICENSE.txt
Requires-Dist: pandas (>=1.5.2)
Requires-Dist: numpy (>=1.22.4)
Requires-Dist: numba (>=0.56.4)
Requires-Dist: requests (>=2.23.0)
Requires-Dist: polyline (>=1.4.0)
Requires-Dist: rasterio (>=1.2.10)
Requires-Dist: meteostat (>=1.6.3)
